pdf2odt/__init__.py
pdf2odt/core.py
pdf2odt/locale/es/LC_MESSAGES/pdf2odt.mo
pdf2odt/locale/es.po
pdf2odt/locale/fr/LC_MESSAGES/pdf2odt.mo
pdf2odt/locale/fr.po
pdf2odt/locale/pdf2odt.pot
pdf2odt/poethepoet.py
pdf2odt-1.0.0.dist-info/LICENSE
pdf2odt-1.0.0.dist-info/METADATA
pdf2odt-1.0.0.dist-info/WHEEL
pdf2odt-1.0.0.dist-info/entry_points.txt
pdf2odt-1.0.0.dist-info/RECORD
