Metadata-Version: 2.1
Name: pdf2odt
Version: 1.0.0
Summary: Converts a pdf into a Libreoffice Writer document, with images resized to A4 and anchored as character
License: GPL-3.0 license
Author: turulomio
Author-email: turulomio@yahoo.es
Requires-Python: >=3.12,<4.0
Classifier: License :: Other/Proprietary License
Classifier: Programming Language :: Python :: 3
Classifier: Programming Language :: Python :: 3.12
Classifier: Programming Language :: Python :: 3.13
Requires-Dist: colorama (>=0.4.6,<0.5.0)
Requires-Dist: tqdm (>=4.67.1,<5.0.0)
Requires-Dist: unogenerator (>=1.0.0,<2.0.0)
